LICENSE
MANIFEST.in
NOTICE
README.md
setup.py
tests/__init__.py
tests/mock_http_server.py
tests/test_yubico.py
tests/utils.py
yubico/__init__.py
yubico/modhex.py
yubico/otp.py
yubico/yubico.py
yubico/yubico_exceptions.py
yubico.egg-info/PKG-INFO
yubico.egg-info/SOURCES.txt
yubico.egg-info/dependency_links.txt
yubico.egg-info/requires.txt
yubico.egg-info/top_level.txt